{"44200.mgmt03": { "Username" :"bhanuday", "Queue" :"smallsb", "Jobname" :"sb_hold", "Nodes" :"2", "Task" :"32", "RequiredTime" :"120:0", "State" :"H"
, "Elapsed_Time" :"--", "Exec_host" :[]}
,"49915.mgmt03": { "Username" :"shreyaag", "Queue" :"smallsb", "Jobname" :"us4", "Nodes" :"2", "Task" :"32", "RequiredTime" :"120:0", "State" :"H"
, "Elapsed_Time" :"--", "Exec_host" :[]}
,"97118.mgmt03": { "Username" :"arnesh", "Queue" :"smallsb", "Jobname" :"AR4maxcl", "Nodes" :"2", "Task" :"32", "RequiredTime" :"120:0", "State" :"H"
, "Elapsed_Time" :"--", "Exec_host" :[]}
,"52906.mgmt03": { "Username" :"yuvrj", "Queue" :"small", "Jobname" :"test", "Nodes" :"4", "Task" :"32", "RequiredTime" :"120:0", "State" :"H"
, "Elapsed_Time" :"--", "Exec_host" :[]}
,"88041.mgmt03": { "Username" :"arnesh", "Queue" :"mediumsb", "Jobname" :"test1", "Nodes" :"6", "Task" :"96", "RequiredTime" :"96:00", "State" :"H"
, "Elapsed_Time" :"--", "Exec_host" :[]}
,"135008.mgmt03": { "Username" :"kanishka", "Queue" :"medium", "Jobname" :"medium", "Nodes" :"4", "Task" :"32", "RequiredTime" :"96:00", "State" :"H"
, "Elapsed_Time" :"--", "Exec_host" :[]}
,"135441.mgmt03": { "Username" :"abirlal", "Queue" :"small", "Jobname" :"MoO2", "Nodes" :"1", "Task" :"10", "RequiredTime" :"12:00", "State" :"Q"
, "Elapsed_Time" :"--", "Exec_host" :[]}
,"135443.mgmt03": { "Username" :"abirlal", "Queue" :"small", "Jobname" :"MoO2", "Nodes" :"1", "Task" :"10", "RequiredTime" :"12:00", "State" :"Q"
, "Elapsed_Time" :"--", "Exec_host" :[]}
,"140876.mgmt03": { "Username" :"lgaur", "Queue" :"small", "Jobname" :"case_2", "Nodes" :"1", "Task" :"16", "RequiredTime" :"120:0", "State" :"Q"
, "Elapsed_Time" :"--", "Exec_host" :[]}
,"136847.mgmt03": { "Username" :"ragamaye", "Queue" :"medium", "Jobname" :"med2", "Nodes" :"2", "Task" :"40", "RequiredTime" :"96:00", "State" :"Q"
, "Elapsed_Time" :"--", "Exec_host" :[]}
,"99474.mgmt03": { "Username" :"arnesh", "Queue" :"medium", "Jobname" :"AR4mincl", "Nodes" :"4", "Task" :"32", "RequiredTime" :"96:00", "State" :"H"
, "Elapsed_Time" :"--", "Exec_host" :[]}
,"53301.mgmt03": { "Username" :"yuvrj", "Queue" :"medium", "Jobname" :"AR3_A4", "Nodes" :"10", "Task" :"80", "RequiredTime" :"96:00", "State" :"H"
, "Elapsed_Time" :"--", "Exec_host" :[]}
,"88029.mgmt03": { "Username" :"arnesh", "Queue" :"large", "Jobname" :"AR2_M2.2", "Nodes" :"16", "Task" :"128", "RequiredTime" :"72:00", "State" :"H"
, "Elapsed_Time" :"--", "Exec_host" :[]}
,"135971.mgmt03": { "Username" :"lgaur", "Queue" :"small", "Jobname" :"axi_9", "Nodes" :"4", "Task" :"32", "RequiredTime" :"120:0", "State" :"H"
, "Elapsed_Time" :"--", "Exec_host" :[]}
,"136264.mgmt03": { "Username" :"lgaur", "Queue" :"smallsb", "Jobname" :"axi_5", "Nodes" :"2", "Task" :"32", "RequiredTime" :"120:0", "State" :"H"
, "Elapsed_Time" :"--", "Exec_host" :[]}
,"139046.mgmt03": { "Username" :"tulsiram", "Queue" :"large", "Jobname" :"AoA20", "Nodes" :"20", "Task" :"160", "RequiredTime" :"72:00", "State" :"H"
, "Elapsed_Time" :"--", "Exec_host" :[]}
,"95072.mgmt03": { "Username" :"gchopra", "Queue" :"small", "Jobname" :"Up130m10", "Nodes" :"4", "Task" :"32", "RequiredTime" :"120:0", "State" :"H"
, "Elapsed_Time" :"--", "Exec_host" :[]}
,"100987.mgmt03": { "Username" :"gchopra", "Queue" :"medium", "Jobname" :"Up110m100n", "Nodes" :"6", "Task" :"48", "RequiredTime" :"96:00", "State" :"H"
, "Elapsed_Time" :"--", "Exec_host" :[]}
,"141639.mgmt03": { "Username" :"adityad", "Queue" :"medium", "Jobname" :"2Up6.5", "Nodes" :"4", "Task" :"32", "RequiredTime" :"96:00", "State" :"H"
, "Elapsed_Time" :"--", "Exec_host" :[]}
,"141644.mgmt03": { "Username" :"adityad", "Queue" :"small", "Jobname" :"2Up7.5", "Nodes" :"4", "Task" :"32", "RequiredTime" :"120:0", "State" :"H"
, "Elapsed_Time" :"--", "Exec_host" :[]}
,"141646.mgmt03": { "Username" :"adityad", "Queue" :"smallsb", "Jobname" :"2Up8", "Nodes" :"2", "Task" :"32", "RequiredTime" :"120:0", "State" :"H"
, "Elapsed_Time" :"--", "Exec_host" :[]}
,"53129.mgmt03": { "Username" :"yuvrj", "Queue" :"smallsb", "Jobname" :"test", "Nodes" :"2", "Task" :"32", "RequiredTime" :"120:0", "State" :"H"
, "Elapsed_Time" :"--", "Exec_host" :[]}
,"141661.mgmt03": { "Username" :"adityad", "Queue" :"mediumsb", "Jobname" :"2Up11", "Nodes" :"2", "Task" :"32", "RequiredTime" :"96:00", "State" :"H"
, "Elapsed_Time" :"--", "Exec_host" :[]}
,"142002.mgmt03": { "Username" :"vvmk", "Queue" :"large", "Jobname" :"SMA2", "Nodes" :"16", "Task" :"128", "RequiredTime" :"72:00", "State" :"H"
, "Elapsed_Time" :"--", "Exec_host" :[]}
,"142003.mgmt03": { "Username" :"vvmk", "Queue" :"large", "Jobname" :"SMA2", "Nodes" :"16", "Task" :"128", "RequiredTime" :"72:00", "State" :"H"
, "Elapsed_Time" :"--", "Exec_host" :[]}
,"142005.mgmt03": { "Username" :"vvmk", "Queue" :"medium", "Jobname" :"Smog", "Nodes" :"4", "Task" :"32", "RequiredTime" :"96:00", "State" :"H"
, "Elapsed_Time" :"--", "Exec_host" :[]}
,"142006.mgmt03": { "Username" :"vvmk", "Queue" :"medium", "Jobname" :"Smog", "Nodes" :"4", "Task" :"32", "RequiredTime" :"96:00", "State" :"H"
, "Elapsed_Time" :"--", "Exec_host" :[]}
,"142079[].mgmt03": { "Username" :"thejak", "Queue" :"small", "Jobname" :"S32", "Nodes" :"4", "Task" :"32", "RequiredTime" :"120:0", "State" :"H"
, "Elapsed_Time" :"--", "Exec_host" :[]}
,"134052.mgmt03": { "Username" :"tulsiram", "Queue" :"mediumsb", "Jobname" :"Up100m100f", "Nodes" :"2", "Task" :"32", "RequiredTime" :"96:00", "State" :"H"
, "Elapsed_Time" :"--", "Exec_host" :[]}
,"145442[].mgmt03": { "Username" :"thejak", "Queue" :"medium", "Jobname" :"fig8case", "Nodes" :"12", "Task" :"96", "RequiredTime" :"96:00", "State" :"H"
, "Elapsed_Time" :"--", "Exec_host" :[]}
,"146647[].mgmt03": { "Username" :"prasanna", "Queue" :"small", "Jobname" :"S32", "Nodes" :"4", "Task" :"32", "RequiredTime" :"120:0", "State" :"H"
, "Elapsed_Time" :"--", "Exec_host" :[]}
,"146648[].mgmt03": { "Username" :"prasanna", "Queue" :"smallsb", "Jobname" :"S32", "Nodes" :"2", "Task" :"32", "RequiredTime" :"120:0", "State" :"H"
, "Elapsed_Time" :"--", "Exec_host" :[]}
,"140585.mgmt03": { "Username" :"mfurquan", "Queue" :"medium", "Jobname" :"Re100Up180", "Nodes" :"4", "Task" :"32", "RequiredTime" :"96:00", "State" :"H"
, "Elapsed_Time" :"--", "Exec_host" :[]}
,"148115[].mgmt03": { "Username" :"thejak", "Queue" :"large", "Jobname" :"fig13plasm", "Nodes" :"16", "Task" :"128", "RequiredTime" :"72:00", "State" :"H"
, "Elapsed_Time" :"--", "Exec_host" :[]}
,"134193.mgmt03": { "Username" :"gchopra", "Queue" :"mediumsb", "Jobname" :"Up145m10fr", "Nodes" :"2", "Task" :"32", "RequiredTime" :"96:00", "State" :"H"
, "Elapsed_Time" :"--", "Exec_host" :[]}
,"114351.mgmt03": { "Username" :"gchopra", "Queue" :"smallsb", "Jobname" :"Up7m5f8", "Nodes" :"2", "Task" :"32", "RequiredTime" :"120:0", "State" :"H"
, "Elapsed_Time" :"--", "Exec_host" :[]}
,"210190.mgmt03": { "Username" :"khanaqib", "Queue" :"medium", "Jobname" :"PDR", "Nodes" :"2", "Task" :"32", "RequiredTime" :"96:00", "State" :"H"
, "Elapsed_Time" :"--", "Exec_host" :[]}
,"156227[].mgmt03": { "Username" :"varman", "Queue" :"large", "Jobname" :"Case-2b", "Nodes" :"32", "Task" :"256", "RequiredTime" :"72:00", "State" :"H"
, "Elapsed_Time" :"--", "Exec_host" :[]}
,"105331.mgmt03": { "Username" :"mfurquan", "Queue" :"mediumsb", "Jobname" :"Up100m10ne", "Nodes" :"3", "Task" :"48", "RequiredTime" :"96:00", "State" :"H"
, "Elapsed_Time" :"--", "Exec_host" :[]}
,"198353.mgmt03": { "Username" :"ragamaye", "Queue" :"medium", "Jobname" :"med1", "Nodes" :"2", "Task" :"40", "RequiredTime" :"96:00", "State" :"Q"
, "Elapsed_Time" :"--", "Exec_host" :[]}
,"198868.mgmt03": { "Username" :"ankitsb", "Queue" :"large", "Jobname" :"2dRTI_new", "Nodes" :"16", "Task" :"128", "RequiredTime" :"72:00", "State" :"H"
, "Elapsed_Time" :"--", "Exec_host" :[]}
,"199548.mgmt03": { "Username" :"yuvrj", "Queue" :"large", "Jobname" :"AoA20", "Nodes" :"20", "Task" :"160", "RequiredTime" :"72:00", "State" :"H"
, "Elapsed_Time" :"--", "Exec_host" :[]}
,"199985.mgmt03": { "Username" :"gaman", "Queue" :"small", "Jobname" :"test", "Nodes" :"1", "Task" :"20", "RequiredTime" :"120:0", "State" :"Q"
, "Elapsed_Time" :"--", "Exec_host" :[]}
,"67463.mgmt03": { "Username" :"mfurquan", "Queue" :"large", "Jobname" :"1.2e5_R11", "Nodes" :"32", "Task" :"256", "RequiredTime" :"72:00", "State" :"H"
, "Elapsed_Time" :"--", "Exec_host" :[]}
,"200102.mgmt03": { "Username" :"bbhatia", "Queue" :"small", "Jobname" :"FlT25", "Nodes" :"2", "Task" :"32", "RequiredTime" :"02:00", "State" :"H"
, "Elapsed_Time" :"--", "Exec_host" :[]}
,"114405.mgmt03": { "Username" :"mfurquan", "Queue" :"small", "Jobname" :"Up70m5f80", "Nodes" :"4", "Task" :"32", "RequiredTime" :"120:0", "State" :"H"
, "Elapsed_Time" :"--", "Exec_host" :[]}
,"200297.mgmt03": { "Username" :"adityad", "Queue" :"large", "Jobname" :"AoA9", "Nodes" :"16", "Task" :"128", "RequiredTime" :"72:00", "State" :"H"
, "Elapsed_Time" :"--", "Exec_host" :[]}
,"116467.mgmt03": { "Username" :"tulsiram", "Queue" :"smallsb", "Jobname" :"Up130m100n", "Nodes" :"2", "Task" :"32", "RequiredTime" :"120:0", "State" :"H"
, "Elapsed_Time" :"--", "Exec_host" :[]}
,"137351.mgmt03": { "Username" :"mfurquan", "Queue" :"smallsb", "Jobname" :"Up67m5f70l", "Nodes" :"2", "Task" :"32", "RequiredTime" :"120:0", "State" :"H"
, "Elapsed_Time" :"--", "Exec_host" :[]}
,"95074.mgmt03": { "Username" :"tulsiram", "Queue" :"medium", "Jobname" :"Up138m100", "Nodes" :"4", "Task" :"32", "RequiredTime" :"96:00", "State" :"H"
, "Elapsed_Time" :"--", "Exec_host" :[]}
,"203258[].mgmt03": { "Username" :"thejak", "Queue" :"small", "Jobname" :"case2", "Nodes" :"2", "Task" :"16", "RequiredTime" :"120:0", "State" :"H"
, "Elapsed_Time" :"--", "Exec_host" :[]}
,"203080.mgmt03": { "Username" :"koleyb", "Queue" :"large", "Jobname" :"Re10k_bp_1", "Nodes" :"32", "Task" :"256", "RequiredTime" :"72:00", "State" :"H"
, "Elapsed_Time" :"--", "Exec_host" :[]}
,"204235[].mgmt03": { "Username" :"mbraj", "Queue" :"smallsb", "Jobname" :"S32", "Nodes" :"2", "Task" :"32", "RequiredTime" :"120:0", "State" :"H"
, "Elapsed_Time" :"--", "Exec_host" :[]}
,"205349[].mgmt03": { "Username" :"prasanna", "Queue" :"mediumsb", "Jobname" :"SHM1-Fig7b", "Nodes" :"4", "Task" :"64", "RequiredTime" :"96:00", "State" :"H"
, "Elapsed_Time" :"--", "Exec_host" :[]}
,"105081.mgmt03": { "Username" :"tulsiram", "Queue" :"small", "Jobname" :"Up138m100", "Nodes" :"4", "Task" :"32", "RequiredTime" :"120:0", "State" :"H"
, "Elapsed_Time" :"--", "Exec_host" :[]}
,"206094.mgmt03": { "Username" :"mitesht", "Queue" :"mediumsb", "Jobname" :"RT", "Nodes" :"4", "Task" :"64", "RequiredTime" :"96:00", "State" :"H"
, "Elapsed_Time" :"--", "Exec_host" :[]}
,"206414.mgmt03": { "Username" :"amanpar", "Queue" :"mediumsb", "Jobname" :"H", "Nodes" :"6", "Task" :"96", "RequiredTime" :"96:00", "State" :"H"
, "Elapsed_Time" :"--", "Exec_host" :[]}
,"206966[].mgmt03": { "Username" :"prasanna", "Queue" :"smallsb", "Jobname" :"S32", "Nodes" :"2", "Task" :"32", "RequiredTime" :"120:0", "State" :"H"
, "Elapsed_Time" :"--", "Exec_host" :[]}
,"206967[].mgmt03": { "Username" :"prasanna", "Queue" :"small", "Jobname" :"Ae0.0002", "Nodes" :"4", "Task" :"32", "RequiredTime" :"120:0", "State" :"H"
, "Elapsed_Time" :"--", "Exec_host" :[]}
,"206973[].mgmt03": { "Username" :"prasanna", "Queue" :"mediumsb", "Jobname" :"Msb96", "Nodes" :"6", "Task" :"96", "RequiredTime" :"96:00", "State" :"H"
, "Elapsed_Time" :"--", "Exec_host" :[]}
,"206974[].mgmt03": { "Username" :"prasanna", "Queue" :"medium", "Jobname" :"M96", "Nodes" :"12", "Task" :"96", "RequiredTime" :"96:00", "State" :"H"
, "Elapsed_Time" :"--", "Exec_host" :[]}
,"206977[].mgmt03": { "Username" :"thejak", "Queue" :"medium", "Jobname" :"M96", "Nodes" :"12", "Task" :"96", "RequiredTime" :"96:00", "State" :"H"
, "Elapsed_Time" :"--", "Exec_host" :[]}
,"206979[].mgmt03": { "Username" :"thejak", "Queue" :"smallsb", "Jobname" :"Ssb32", "Nodes" :"2", "Task" :"32", "RequiredTime" :"120:0", "State" :"H"
, "Elapsed_Time" :"--", "Exec_host" :[]}
,"206982[].mgmt03": { "Username" :"pksharma", "Queue" :"mediumsb", "Jobname" :"Msb96", "Nodes" :"6", "Task" :"96", "RequiredTime" :"96:00", "State" :"H"
, "Elapsed_Time" :"--", "Exec_host" :[]}
,"206983[].mgmt03": { "Username" :"pksharma", "Queue" :"small", "Jobname" :"S32", "Nodes" :"4", "Task" :"32", "RequiredTime" :"120:0", "State" :"H"
, "Elapsed_Time" :"--", "Exec_host" :[]}
,"206984[].mgmt03": { "Username" :"pksharma", "Queue" :"smallsb", "Jobname" :"Ssb32", "Nodes" :"2", "Task" :"32", "RequiredTime" :"120:0", "State" :"H"
, "Elapsed_Time" :"--", "Exec_host" :[]}
,"206986[].mgmt03": { "Username" :"mbraj", "Queue" :"mediumsb", "Jobname" :"Msb96", "Nodes" :"6", "Task" :"96", "RequiredTime" :"96:00", "State" :"H"
, "Elapsed_Time" :"--", "Exec_host" :[]}
,"206987[].mgmt03": { "Username" :"mbraj", "Queue" :"medium", "Jobname" :"M96", "Nodes" :"12", "Task" :"96", "RequiredTime" :"96:00", "State" :"H"
, "Elapsed_Time" :"--", "Exec_host" :[]}
,"206988[].mgmt03": { "Username" :"mbraj", "Queue" :"smallsb", "Jobname" :"S32", "Nodes" :"2", "Task" :"32", "RequiredTime" :"120:0", "State" :"H"
, "Elapsed_Time" :"--", "Exec_host" :[]}
,"207195[].mgmt03": { "Username" :"prasanna", "Queue" :"large", "Jobname" :"3D_LNSE_W2", "Nodes" :"32", "Task" :"256", "RequiredTime" :"72:00", "State" :"H"
, "Elapsed_Time" :"--", "Exec_host" :[]}
,"207337[].mgmt03": { "Username" :"thejak", "Queue" :"large", "Jobname" :"3D_LNSE_W2", "Nodes" :"16", "Task" :"128", "RequiredTime" :"72:00", "State" :"H"
, "Elapsed_Time" :"--", "Exec_host" :[]}
,"207717.mgmt03": { "Username" :"bhawan", "Queue" :"large", "Jobname" :"case_10k.d", "Nodes" :"30", "Task" :"240", "RequiredTime" :"72:00", "State" :"Q"
, "Elapsed_Time" :"--", "Exec_host" :[]}
,"208125.mgmt03": { "Username" :"mitesht", "Queue" :"large", "Jobname" :"RT", "Nodes" :"32", "Task" :"256", "RequiredTime" :"72:00", "State" :"H"
, "Elapsed_Time" :"--", "Exec_host" :[]}
,"209020[].mgmt03": { "Username" :"viknesh", "Queue" :"medium", "Jobname" :"R96", "Nodes" :"12", "Task" :"96", "RequiredTime" :"96:00", "State" :"H"
, "Elapsed_Time" :"--", "Exec_host" :[]}
,"47030.mgmt03": { "Username" :"khanaqib", "Queue" :"mediumsb", "Jobname" :"Msb2", "Nodes" :"6", "Task" :"96", "RequiredTime" :"96:00", "State" :"H"
, "Elapsed_Time" :"--", "Exec_host" :[]}
,"140704.mgmt03": { "Username" :"khanaqib", "Queue" :"medium", "Jobname" :"med1", "Nodes" :"12", "Task" :"96", "RequiredTime" :"96:00", "State" :"H"
, "Elapsed_Time" :"--", "Exec_host" :[]}
,"210197.mgmt03": { "Username" :"jawahar", "Queue" :"mediumsb", "Jobname" :"AoA8_AR6", "Nodes" :"6", "Task" :"96", "RequiredTime" :"96:00", "State" :"H"
, "Elapsed_Time" :"--", "Exec_host" :[]}
,"47033.mgmt03": { "Username" :"khanaqib", "Queue" :"large", "Jobname" :"L2", "Nodes" :"32", "Task" :"256", "RequiredTime" :"72:00", "State" :"H"
, "Elapsed_Time" :"--", "Exec_host" :[]}
,"210952.mgmt03": { "Username" :"abhisidd", "Queue" :"medium", "Jobname" :"PDR", "Nodes" :"2", "Task" :"32", "RequiredTime" :"96:00", "State" :"H"
, "Elapsed_Time" :"--", "Exec_host" :[]}
,"210979.mgmt03": { "Username" :"jawahar", "Queue" :"large", "Jobname" :"AoA12_AR10", "Nodes" :"20", "Task" :"160", "RequiredTime" :"72:00", "State" :"H"
, "Elapsed_Time" :"--", "Exec_host" :[]}
,"210993.mgmt03": { "Username" :"saptar", "Queue" :"large", "Jobname" :"case_10k.d", "Nodes" :"16", "Task" :"128", "RequiredTime" :"72:00", "State" :"Q"
, "Elapsed_Time" :"--", "Exec_host" :[]}
,"210994.mgmt03": { "Username" :"saptar", "Queue" :"medium", "Jobname" :"case_20k.d", "Nodes" :"12", "Task" :"96", "RequiredTime" :"96:00", "State" :"R"
, "Elapsed_Time" :"31:06", "Exec_host" :["cn231","cn268","cn257","cn199","cn217","cn256","cn265","cn282","cn237","cn273","cn224","cn263"]}
,"210997.mgmt03": { "Username" :"kritama", "Queue" :"small", "Jobname" :"2.4", "Nodes" :"4", "Task" :"32", "RequiredTime" :"120:0", "State" :"R"
, "Elapsed_Time" :"51:58", "Exec_host" :["cn305","cn325","cn285","cn329"]}
,"211001.mgmt03": { "Username" :"abhisidd", "Queue" :"smallsb", "Jobname" :"PDRTA", "Nodes" :"2", "Task" :"32", "RequiredTime" :"120:0", "State" :"H"
, "Elapsed_Time" :"--", "Exec_host" :[]}
,"211054.mgmt03": { "Username" :"dmonika", "Queue" :"smallsb", "Jobname" :"kmc_run", "Nodes" :"1", "Task" :"16", "RequiredTime" :"120:0", "State" :"R"
, "Elapsed_Time" :"97:13", "Exec_host" :["cn446"]}
,"211092.mgmt03": { "Username" :"rekha", "Queue" :"large", "Jobname" :"4nw1212", "Nodes" :"30", "Task" :"240", "RequiredTime" :"72:00", "State" :"R"
, "Elapsed_Time" :"55:38", "Exec_host" :["cn177","cn151","cn106","cn088","cn078","cn066","cn109","cn167","cn058","cn170","cn174","cn175","cn165","cn098","cn028","cn125","cn126","cn037","cn173","cn034","cn150","cn012","cn121","cn032","cn006","cn023","cn047","cn005","cn075","cn094"]}
,"211093.mgmt03": { "Username" :"rekha", "Queue" :"medium", "Jobname" :"4nw99", "Nodes" :"12", "Task" :"96", "RequiredTime" :"96:00", "State" :"R"
, "Elapsed_Time" :"89:58", "Exec_host" :["cn193","cn249","cn188","cn226","cn240","cn235","cn195","cn247","cn200","cn213","cn225","cn185"]}
,"211095.mgmt03": { "Username" :"sayeed", "Queue" :"medium", "Jobname" :"Ni6Scan", "Nodes" :"4", "Task" :"32", "RequiredTime" :"96:00", "State" :"R"
, "Elapsed_Time" :"91:18", "Exec_host" :["cn210","cn221","cn222","cn214"]}
,"211098.mgmt03": { "Username" :"rekha", "Queue" :"large", "Jobname" :"2nw1212", "Nodes" :"30", "Task" :"240", "RequiredTime" :"72:00", "State" :"Q"
, "Elapsed_Time" :"--", "Exec_host" :[]}
,"211099.mgmt03": { "Username" :"rekha", "Queue" :"medium", "Jobname" :"2nw99", "Nodes" :"12", "Task" :"96", "RequiredTime" :"96:00", "State" :"Q"
, "Elapsed_Time" :"--", "Exec_host" :[]}
,"211109.mgmt03": { "Username" :"kshashi", "Queue" :"small", "Jobname" :"Cu4CordLs", "Nodes" :"2", "Task" :"16", "RequiredTime" :"120:0", "State" :"R"
, "Elapsed_Time" :"80:18", "Exec_host" :["cn335","cn328"]}
,"206338.mgmt03": { "Username" :"amanpar", "Queue" :"large", "Jobname" :"H", "Nodes" :"16", "Task" :"128", "RequiredTime" :"72:00", "State" :"H"
, "Elapsed_Time" :"--", "Exec_host" :[]}
,"211111.mgmt03": { "Username" :"pkpandey", "Queue" :"small", "Jobname" :"5.6", "Nodes" :"4", "Task" :"32", "RequiredTime" :"120:0", "State" :"R"
, "Elapsed_Time" :"78:41", "Exec_host" :["cn324","cn332","cn317","cn298"]}
,"211112.mgmt03": { "Username" :"pkpandey", "Queue" :"small", "Jobname" :"5.6", "Nodes" :"4", "Task" :"32", "RequiredTime" :"120:0", "State" :"Q"
, "Elapsed_Time" :"--", "Exec_host" :[]}
,"211113.mgmt03": { "Username" :"pkpandey", "Queue" :"medium", "Jobname" :"5.5", "Nodes" :"4", "Task" :"32", "RequiredTime" :"96:00", "State" :"R"
, "Elapsed_Time" :"78:29", "Exec_host" :["cn197","cn241","cn283","cn205"]}
,"211114.mgmt03": { "Username" :"pkpandey", "Queue" :"medium", "Jobname" :"5.5", "Nodes" :"4", "Task" :"32", "RequiredTime" :"96:00", "State" :"Q"
, "Elapsed_Time" :"--", "Exec_host" :[]}
,"211124.mgmt03": { "Username" :"gunvirs", "Queue" :"large", "Jobname" :"AUSMEulerS", "Nodes" :"32", "Task" :"256", "RequiredTime" :"72:00", "State" :"R"
, "Elapsed_Time" :"06:34", "Exec_host" :["cn015","cn021","cn077","cn097","cn090","cn068","cn079","cn166","cn044","cn178","cn033","cn153","cn127","cn073","cn043","cn064","cn113","cn053","cn112","cn099","cn096","cn013","cn184","cn011","cn117","cn081","cn100","cn084","cn157","cn014","cn159","cn181"]}
,"211130.mgmt03": { "Username" :"dolly", "Queue" :"medium", "Jobname" :"18daCD", "Nodes" :"4", "Task" :"32", "RequiredTime" :"96:00", "State" :"R"
, "Elapsed_Time" :"70:51", "Exec_host" :["cn234","cn264","cn255","cn252"]}
,"211132.mgmt03": { "Username" :"akhilesh", "Queue" :"medium", "Jobname" :"CuLazoph6S", "Nodes" :"4", "Task" :"32", "RequiredTime" :"96:00", "State" :"R"
, "Elapsed_Time" :"66:40", "Exec_host" :["cn206","cn239","cn192","cn271"]}
,"211134.mgmt03": { "Username" :"abila", "Queue" :"medium", "Jobname" :"miniini.pb", "Nodes" :"2", "Task" :"40", "RequiredTime" :"96:00", "State" :"Q"
, "Elapsed_Time" :"--", "Exec_host" :[]}
,"211135.mgmt03": { "Username" :"abila", "Queue" :"small", "Jobname" :"smini.pbs", "Nodes" :"1", "Task" :"20", "RequiredTime" :"120:0", "State" :"Q"
, "Elapsed_Time" :"--", "Exec_host" :[]}
,"211151.mgmt03": { "Username" :"vrahul", "Queue" :"mediumsb", "Jobname" :"umb_0.5", "Nodes" :"4", "Task" :"64", "RequiredTime" :"96:00", "State" :"R"
, "Elapsed_Time" :"49:23", "Exec_host" :["cn414","cn377","cn406","cn373"]}
,"211166.mgmt03": { "Username" :"bapans", "Queue" :"medium", "Jobname" :"rrDPEAp", "Nodes" :"4", "Task" :"32", "RequiredTime" :"96:00", "State" :"R"
, "Elapsed_Time" :"44:52", "Exec_host" :["cn267","cn278","cn270","cn219"]}
,"211168.mgmt03": { "Username" :"ahilan", "Queue" :"small", "Jobname" :"Cyl_DSMC", "Nodes" :"1", "Task" :"20", "RequiredTime" :"120:0", "State" :"Q"
, "Elapsed_Time" :"--", "Exec_host" :[]}
,"211172.mgmt03": { "Username" :"kritama", "Queue" :"small", "Jobname" :"2.4", "Nodes" :"4", "Task" :"32", "RequiredTime" :"120:0", "State" :"Q"
, "Elapsed_Time" :"--", "Exec_host" :[]}
,"211173.mgmt03": { "Username" :"sonuv", "Queue" :"small", "Jobname" :"SnS", "Nodes" :"4", "Task" :"32", "RequiredTime" :"120:0", "State" :"R"
, "Elapsed_Time" :"33:06", "Exec_host" :["cn334","cn333","cn315","cn313"]}
,"211174.mgmt03": { "Username" :"sonuv", "Queue" :"medium", "Jobname" :"Sonu", "Nodes" :"4", "Task" :"32", "RequiredTime" :"96:00", "State" :"R"
, "Elapsed_Time" :"16:11", "Exec_host" :["cn218","cn207","cn276","cn186"]}
,"211175.mgmt03": { "Username" :"msnaim", "Queue" :"large", "Jobname" :"V_RING130", "Nodes" :"32", "Task" :"256", "RequiredTime" :"72:00", "State" :"R"
, "Elapsed_Time" :"31:31", "Exec_host" :["cn154","cn163","cn070","cn095","cn133","cn148","cn160","cn071","cn016","cn036","cn122","cn082","cn164","cn008","cn051","cn057","cn072","cn130","cn087","cn139","cn172","cn035","cn027","cn114","cn158","cn067","cn074","cn146","cn091","cn009","cn056","cn039"]}
,"211188.mgmt03": { "Username" :"aadit", "Queue" :"small", "Jobname" :"case_140k.", "Nodes" :"4", "Task" :"32", "RequiredTime" :"120:0", "State" :"R"
, "Elapsed_Time" :"28:55", "Exec_host" :["cn336","cn307","cn289","cn337"]}
,"211193.mgmt03": { "Username" :"aadit", "Queue" :"small", "Jobname" :"Ra.dat", "Nodes" :"3", "Task" :"24", "RequiredTime" :"120:0", "State" :"Q"
, "Elapsed_Time" :"--", "Exec_host" :[]}
,"211196.mgmt03": { "Username" :"razia", "Queue" :"mediumsb", "Jobname" :"middle_Wad", "Nodes" :"4", "Task" :"64", "RequiredTime" :"96:00", "State" :"R"
, "Elapsed_Time" :"21:51", "Exec_host" :["cn410","cn372","cn388","cn394"]}
,"211199.mgmt03": { "Username" :"bapans", "Queue" :"small", "Jobname" :"15daP", "Nodes" :"2", "Task" :"16", "RequiredTime" :"120:0", "State" :"R"
, "Elapsed_Time" :"20:42", "Exec_host" :["cn302","cn286"]}
,"211201.mgmt03": { "Username" :"dolly", "Queue" :"small", "Jobname" :"sPPDAp", "Nodes" :"2", "Task" :"16", "RequiredTime" :"120:0", "State" :"R"
, "Elapsed_Time" :"20:28", "Exec_host" :["cn309","cn295"]}
,"211208.mgmt03": { "Username" :"aadit", "Queue" :"workq", "Jobname" :"STDIN", "Nodes" :"1", "Task" :"1", "RequiredTime" :"02:00", "State" :"R"
, "Elapsed_Time" :"00:00", "Exec_host" :["cn360"]}
,"211210.mgmt03": { "Username" :"dmonika", "Queue" :"large", "Jobname" :"kmc_run", "Nodes" :"16", "Task" :"128", "RequiredTime" :"72:00", "State" :"R"
, "Elapsed_Time" :"08:45", "Exec_host" :["cn046","cn092","cn004","cn045","cn135","cn115","cn108","cn103","cn152","cn136","cn085","cn129","cn169","cn065","cn030","cn003"]}
,"211215.mgmt03": { "Username" :"aakhil", "Queue" :"workqsb", "Jobname" :"STDIN", "Nodes" :"1", "Task" :"1", "RequiredTime" :"02:00", "State" :"R"
, "Elapsed_Time" :"00:00", "Exec_host" :["cn463"]}
,"211219.mgmt03": { "Username" :"nidhig", "Queue" :"large", "Jobname" :"kmc_run", "Nodes" :"16", "Task" :"128", "RequiredTime" :"72:00", "State" :"R"
, "Elapsed_Time" :"08:10", "Exec_host" :["cn024","cn104","cn124","cn144","cn038","cn093","cn086","cn120","cn142","cn176","cn083","cn138","cn026","cn069","cn168","cn156"]}
,"211229.mgmt03": { "Username" :"gunvirs", "Queue" :"large", "Jobname" :"AUSMEulerS", "Nodes" :"32", "Task" :"256", "RequiredTime" :"72:00", "State" :"Q"
, "Elapsed_Time" :"--", "Exec_host" :[]}
,"211232.mgmt03": { "Username" :"mrishi", "Queue" :"smallsb", "Jobname" :"q5mmssb.sh", "Nodes" :"2", "Task" :"32", "RequiredTime" :"120:0", "State" :"R"
, "Elapsed_Time" :"05:54", "Exec_host" :["cn417","cn430"]}
,"211236.mgmt03": { "Username" :"amanpar", "Queue" :"large", "Jobname" :"1.4e5", "Nodes" :"30", "Task" :"240", "RequiredTime" :"72:00", "State" :"R"
, "Elapsed_Time" :"05:19", "Exec_host" :["cn134","cn101","cn140","cn179","cn149","cn020","cn042","cn060","cn110","cn162","cn031","cn007","cn063","cn171","cn001","cn029","cn010","cn018","cn116","cn105","cn118","cn111","cn089","cn041","cn040","cn017","cn123","cn137","cn025","cn048"]}
,"211237.mgmt03": { "Username" :"abhisidd", "Queue" :"smallsb", "Jobname" :"prob2", "Nodes" :"2", "Task" :"32", "RequiredTime" :"120:0", "State" :"R"
, "Elapsed_Time" :"05:08", "Exec_host" :["cn439","cn448"]}
,"211239.mgmt03": { "Username" :"abhisidd", "Queue" :"mediumsb", "Jobname" :"prob1", "Nodes" :"2", "Task" :"32", "RequiredTime" :"96:00", "State" :"R"
, "Elapsed_Time" :"05:01", "Exec_host" :["cn411","cn369"]}
,"211252.mgmt03": { "Username" :"mrishi", "Queue" :"mediumsb", "Jobname" :"qmsbDelPar", "Nodes" :"5", "Task" :"80", "RequiredTime" :"96:00", "State" :"R"
, "Elapsed_Time" :"02:29", "Exec_host" :["cn392","cn374","cn370","cn375","cn378"]}
,"211253.mgmt03": { "Username" :"waquar", "Queue" :"workq", "Jobname" :"STDIN", "Nodes" :"1", "Task" :"1", "RequiredTime" :"02:00", "State" :"R"
, "Elapsed_Time" :"00:01", "Exec_host" :["cn363"]}
,"211254.mgmt03": { "Username" :"nidhig", "Queue" :"workq", "Jobname" :"STDIN", "Nodes" :"1", "Task" :"1", "RequiredTime" :"02:00", "State" :"R"
, "Elapsed_Time" :"00:00", "Exec_host" :["cn364"]}
,"211257.mgmt03": { "Username" :"sonuv", "Queue" :"workq", "Jobname" :"STDIN", "Nodes" :"1", "Task" :"1", "RequiredTime" :"02:00", "State" :"R"
, "Elapsed_Time" :"00:00", "Exec_host" :["cn365"]}
,"211258.mgmt03": { "Username" :"nidhig", "Queue" :"workq", "Jobname" :"STDIN", "Nodes" :"1", "Task" :"1", "RequiredTime" :"02:00", "State" :"R"
, "Elapsed_Time" :"00:00", "Exec_host" :["cn361"]}
,"211259.mgmt03": { "Username" :"nidhig", "Queue" :"mediumsb", "Jobname" :"kmc_run", "Nodes" :"2", "Task" :"32", "RequiredTime" :"96:00", "State" :"R"
, "Elapsed_Time" :"00:22", "Exec_host" :["cn376","cn381"]}
,"211260.mgmt03": { "Username" :"nidhig", "Queue" :"smallsb", "Jobname" :"kmc_run", "Nodes" :"1", "Task" :"16", "RequiredTime" :"120:0", "State" :"R"
, "Elapsed_Time" :"00:16", "Exec_host" :["cn428"]}
,"211261.mgmt03": { "Username" :"sonuv", "Queue" :"medium", "Jobname" :"Sonu", "Nodes" :"10", "Task" :"80", "RequiredTime" :"96:00", "State" :"Q"
, "Elapsed_Time" :"--", "Exec_host" :[]}
,"211262.mgmt03": { "Username" :"abhigpt", "Queue" :"mediumsb", "Jobname" :"umb_0.4", "Nodes" :"4", "Task" :"64", "RequiredTime" :"96:00", "State" :"R"
, "Elapsed_Time" :"00:10", "Exec_host" :["cn382","cn396","cn400","cn380"]}
,"211263.mgmt03": { "Username" :"abhigpt", "Queue" :"medium", "Jobname" :"umb_1.8", "Nodes" :"8", "Task" :"64", "RequiredTime" :"96:00", "State" :"R"
, "Elapsed_Time" :"00:07", "Exec_host" :["cn190","cn191","cn243","cn250","cn259","cn202","cn238","cn215"]}
,"211267.mgmt03": { "Username" :"vrahul", "Queue" :"medium", "Jobname" :"umb_0.8", "Nodes" :"10", "Task" :"80", "RequiredTime" :"96:00", "State" :"R"
, "Elapsed_Time" :"00:04", "Exec_host" :["cn194","cn275","cn198","cn203","cn272","cn246","cn244","cn261","cn233","cn251"]}
,"211269.mgmt03": { "Username" :"vrahul", "Queue" :"large", "Jobname" :"umb_1.6", "Nodes" :"16", "Task" :"128", "RequiredTime" :"72:00", "State" :"Q"
, "Elapsed_Time" :"--", "Exec_host" :[]}
,"211270.mgmt03": { "Username" :"aakhil", "Queue" :"smallsb", "Jobname" :"cyl100", "Nodes" :"2", "Task" :"32", "RequiredTime" :"120:0", "State" :"R"
, "Elapsed_Time" :"00:01", "Exec_host" :["cn443","cn423"]}
,"211271.mgmt03": { "Username" :"aakhil", "Queue" :"mediumsb", "Jobname" :"cyl320", "Nodes" :"6", "Task" :"96", "RequiredTime" :"96:00", "State" :"R"
, "Elapsed_Time" :"00:00", "Exec_host" :["cn403","cn409","cn413","cn391","cn397","cn401"]}
}